emrandom/__init__.py
emrandom/correlated.py
emtrain/__init__.py
emtrain/_train.py
emtrain/wrappers.py
emtrain/evaluate/__init__.py
emtrain/hyper/__init__.py
emutils/__init__.py
emutils/args.py
emutils/bayesian_networks.py
emutils/datasets.py
emutils/imports.py
emutils/latex.py
emutils/mlutils.py
emutils/statistics.py
emutils/dsutils/__init__.py
emutils/dsutils/preprocess.py
emutils/dsutils/sample.py
emutils/dsutils/utils.py
emutils/geometry/__init__.py
emutils/geometry/ball.py
emutils/geometry/cone.py
emutils/geometry/lof.py
emutils/geometry/madscaler.py
emutils/geometry/metrics.py
emutils/geometry/normalizer.py
emutils/geometry/percentiler.py
emutils/geometry/quantiletransformer.py
emutils/geometry/utils.py
emutils/hyper/__init__.py
emutils/hyper/_best.py
emutils/hyper/_hyper.py
emutils/hyper/_hyperopt_monkeypatch.py
emutils/hyper/_hyperopt_search.py
emutils/hyper/_spaces.py
emutils/hyper/_utils.py
emutils/load/__init__.py
emutils/load/_pickle.py
emutils/parallel/__init__.py
emutils/parallel/batch.py
emutils/parallel/pool.py
emutils/parallel/utils.py
emutils/rbo/__init__.py
emutils/rbo/_rbo.py
emutils/scripts/__init__.py
emutils/scripts/ipyexport.py
emutils/tf/__init__.py
emutils/tf/math.py
emutils/tf/metrics.py
emutils/utils/__init__.py
emutils/utils/_attrdict.py
emutils/utils/_date.py
emutils/utils/_deprecated.py
emutils/utils/_dict.py
emutils/utils/_ipy.py
emutils/utils/_nx.py
emutils/utils/_profiling.py
emutils/utils/_random.py
emutils/utils/_re.py
emutils/utils/_utils.py
emutils/utils/imports.py
emutils-0.3.2.dist-info/LICENSE
emutils-0.3.2.dist-info/METADATA
emutils-0.3.2.dist-info/WHEEL
emutils-0.3.2.dist-info/entry_points.txt
emutils-0.3.2.dist-info/top_level.txt
emutils-0.3.2.dist-info/RECORD
