Metadata-Version: 2.1
Name: emutils
Version: 0.3.2
Summary: Miscellanous Python Utilities
Home-page: https://github.com/emanuele-albini/emutils
Author: Emanuele Albini
License: UNKNOWN
Project-URL: Documentation, https://emanuele-albini.github.io/emutils
Project-URL: Source Code, https://github.com/emanuele-albini/emutils
Project-URL: Bug Tracker, https://github.com/emanuele-albini/emutils/issues
Project-URL: Author Website, https://www.emanuelealbini.com
Keywords: Utilities
Platform: any
Classifier: Programming Language :: Python :: 3
Classifier: Programming Language :: Python :: 3.6
Classifier: Programming Language :: Python :: 3.7
Classifier: Programming Language :: Python :: 3.8
Classifier: Programming Language :: Python :: 3.9
Classifier: Operating System :: OS Independent
Classifier: Development Status :: 5 - Production/Stable
Classifier: License :: OSI Approved :: MIT License
Requires-Python: >=3.6
License-File: LICENSE
Requires-Dist: numpy
Requires-Dist: scipy
Requires-Dist: pandas
Requires-Dist: matplotlib
Requires-Dist: seaborn
Requires-Dist: networkx
Requires-Dist: scikit-learn
Requires-Dist: tqdm
Requires-Dist: humanize
Requires-Dist: joblib
Requires-Dist: xgboost
Requires-Dist: hyperopt
